{
  "type": "minecraft:crafting_shaped",
  "pattern": [
    "0 2",
    "345",
    "678"
  ],
  "key": {
    "0": {
      "item": "creative_world:compositeplate"
    },
    "2": {
      "item": "creative_world:compositeplate"
    },
    "3": {
      "item": "creative_world:compositeplate"
    },
    "4": {
      "item": "creative_world:compositeplate"
    },
    "5": {
      "item": "creative_world:compositeplate"
    },
    "6": {
      "item": "creative_world:compositeplate"
    },
    "7": {
      "item": "creative_world:compositeplate"
    },
    "8": {
      "item": "creative_world:compositeplate"
    }
  },
  "result": {
    "item": "creative_world:composite_plate_armor_armor_chestplate",
    "count": 1
  }
}